todo/__init__.py
todo/__main__.py
todo/add.py
todo/delete.py
todo/edit.py
todo/globals.py
todo99-0.0.3.dist-info/LICENSE
todo99-0.0.3.dist-info/METADATA
todo99-0.0.3.dist-info/WHEEL
todo99-0.0.3.dist-info/entry_points.txt
todo99-0.0.3.dist-info/top_level.txt
todo99-0.0.3.dist-info/RECORD
