Metadata-Version: 2.1
Name: todo99
Version: 0.0.3
Summary: Minimal todo app implementation
Home-page: https://github.com/plant99/todo
Author: plant99
Author-email: shivashispadhi@gmail.com
License: UNKNOWN
Platform: UNKNOWN
Classifier: Programming Language :: Python :: 3
Classifier: License :: OSI Approved :: MIT License
Classifier: Operating System :: OS Independent
